NmapCankaoZhinan/README.md
NmapCankaoZhinan/__init__.py
NmapCankaoZhinan/__main__.py
NmapCankaoZhinan/file.epub
NmapCankaoZhinan/index.html
NmapCankaoZhinan/css/__init__.py
NmapCankaoZhinan/css/annotations.css
NmapCankaoZhinan/css/main.css
NmapCankaoZhinan/css/normalize.css
NmapCankaoZhinan/css/popup.css
NmapCankaoZhinan/font/__init__.py
NmapCankaoZhinan/font/fontello.eot
NmapCankaoZhinan/font/fontello.svg
NmapCankaoZhinan/font/fontello.ttf
NmapCankaoZhinan/font/fontello.woff
NmapCankaoZhinan/img/__init__.py
NmapCankaoZhinan/img/annotator-glyph-sprite.png
NmapCankaoZhinan/img/annotator-icon-sprite.png
NmapCankaoZhinan/img/apple-touch-icon.png
NmapCankaoZhinan/img/cancelfullscreen.png
NmapCankaoZhinan/img/close.png
NmapCankaoZhinan/img/fullscreen.png
NmapCankaoZhinan/img/loader.gif
NmapCankaoZhinan/img/menu-icon.png
NmapCankaoZhinan/img/save.png
NmapCankaoZhinan/img/saved.png
NmapCankaoZhinan/img/settings-s.png
NmapCankaoZhinan/img/settings.png
NmapCankaoZhinan/img/star.png
NmapCankaoZhinan/js/__init__.py
NmapCankaoZhinan/js/epub.js
NmapCankaoZhinan/js/epub.min.js
NmapCankaoZhinan/js/epub.min.map
NmapCankaoZhinan/js/hooks.min.js
NmapCankaoZhinan/js/hooks.min.map
NmapCankaoZhinan/js/reader.js
NmapCankaoZhinan/js/reader.js.map
NmapCankaoZhinan/js/reader.min.js
NmapCankaoZhinan/js/reader.min.map
NmapCankaoZhinan/js/hooks/__init__.py
NmapCankaoZhinan/js/hooks/extensions/__init__.py
NmapCankaoZhinan/js/hooks/extensions/highlight.js
NmapCankaoZhinan/js/libs/__init__.py
NmapCankaoZhinan/js/libs/jquery.min.js
NmapCankaoZhinan/js/libs/localforage.min.js
NmapCankaoZhinan/js/libs/screenfull.js
NmapCankaoZhinan/js/libs/screenfull.min.js
NmapCankaoZhinan/js/libs/zip.min.js
NmapCankaoZhinan/js/plugins/__init__.py
NmapCankaoZhinan/js/plugins/hypothesis.js
NmapCankaoZhinan/js/plugins/search.js
nmap_cankao_zhinan-2024.3.1.0.dist-info/METADATA
nmap_cankao_zhinan-2024.3.1.0.dist-info/WHEEL
nmap_cankao_zhinan-2024.3.1.0.dist-info/entry_points.txt
nmap_cankao_zhinan-2024.3.1.0.dist-info/top_level.txt
nmap_cankao_zhinan-2024.3.1.0.dist-info/RECORD
